pymdm/__init__.py
pymdm/command_runner.py
pymdm/dialog.py
pymdm/logger.py
pymdm/param_parser.py
pymdm/system_info.py
pymdm/webhook_sender.py
pymdm-0.3.0.dist-info/licenses/LICENSE
pymdm-0.3.0.dist-info/METADATA
pymdm-0.3.0.dist-info/WHEEL
pymdm-0.3.0.dist-info/top_level.txt
pymdm-0.3.0.dist-info/RECORD
