Metadata-Version: 2.4
Name: pymdm
Version: 0.3.0
Summary: Utility functions commonly used in Jamf deployment scripts.
Author-email: Andrew Lerman <info@liquidzoo.io>
Keywords: it,mdm,jamf
Requires-Python: >=3.12
License-File: LICENSE
Provides-Extra: dev
Requires-Dist: build; extra == "dev"
Requires-Dist: pytest>=8.2.2; extra == "dev"
Requires-Dist: pytest-cov>=7.0.0; extra == "dev"
Requires-Dist: requests>=2.32.5; extra == "dev"
Requires-Dist: ruff>=0.5.1; extra == "dev"
Dynamic: license-file
